MANIFEST.in
NEWS.txt
README.rst
setup.py
src/fox/__init__.py
src/fox/cli.py
src/fox/defaults.py
src/fox/helpers.py
src/fox/ipa.py
src/fox/keychain.py
src/fox/provisioningprofile.py
src/fox/util.py
src/fox.egg-info/PKG-INFO
src/fox.egg-info/SOURCES.txt
src/fox.egg-info/dependency_links.txt
src/fox.egg-info/entry_points.txt
src/fox.egg-info/not-zip-safe
src/fox.egg-info/requires.txt
src/fox.egg-info/top_level.txt