Metadata-Version: 1.1
Name: fox
Version: 0.1.9
Summary: An Xcode build tool and utility knife.
Home-page: UNKNOWN
Author: Andy Mroczkowski
Author-email: andy@mrox.net
License: BSD
Keywords: xcode
Platform: UNKNOWN
Classifier: Programming Language :: Python :: 2.7
